MANIFEST.in
README.rst
setup.py
sphinxalchemy/__init__.py
sphinxalchemy/dialect.py
sphinxalchemy/mysqlconnector.py
sphinxalchemy/mysqldb.py
sphinxalchemy/schema.py
sphinxalchemy/sphinxql.py
sphinxalchemy.egg-info/PKG-INFO
sphinxalchemy.egg-info/SOURCES.txt
sphinxalchemy.egg-info/dependency_links.txt
sphinxalchemy.egg-info/entry_points.txt
sphinxalchemy.egg-info/not-zip-safe
sphinxalchemy.egg-info/requires.txt
sphinxalchemy.egg-info/top_level.txt