Metadata-Version: 1.0
Name: sphinxalchemy
Version: 0.5.1
Summary: SQLAlchemy extension for dealing with SphinxQL
Home-page: UNKNOWN
Author: Andrey Popp
Author-email: 8mayday@gmail.com
License: UNKNOWN
Platform: UNKNOWN
